signed_http_req/__init__.py
signed_http_req-1.0.dist-info/DESCRIPTION.rst
signed_http_req-1.0.dist-info/METADATA
signed_http_req-1.0.dist-info/metadata.json
signed_http_req-1.0.dist-info/pbr.json
signed_http_req-1.0.dist-info/RECORD
signed_http_req-1.0.dist-info/top_level.txt
signed_http_req-1.0.dist-info/WHEEL
