Metadata-Version: 2.0
Name: signed-http-req
Version: 1.0
Summary: Python implementation of Signed HTTP Requests for OAuth.
Home-page: https://github.com/its-dirg/signed-http-req
Author: DIRG
Author-email: dirg@its.umu.se
License: Apache 2.0
Platform: UNKNOWN
Classifier: Development Status :: 4 - Beta
Classifier: Intended Audience :: Developers
Classifier: License :: OSI Approved :: Apache Software License
Classifier: Programming Language :: Python
Classifier: Programming Language :: Python :: 3
Classifier: Topic :: Software Development :: Libraries :: Python Modules
Requires-Dist: pyjwkest
